hexbuilder/__init__.py
hexbuilder/builder.py
hexbuilder-1.0.3.dist-info/LICENSE
hexbuilder-1.0.3.dist-info/METADATA
hexbuilder-1.0.3.dist-info/WHEEL
hexbuilder-1.0.3.dist-info/entry_points.txt
hexbuilder-1.0.3.dist-info/top_level.txt
hexbuilder-1.0.3.dist-info/RECORD
