Metadata-Version: 2.1
Name: hexbuilder
Version: 1.0.3
Summary: Command line tool that converts a text file to its representing hex code.
Home-page: https://github.com/davidmaamoaix/HexBuilder
Author: David Ma
Author-email: davidma@davidma.cn
License: MIT
Platform: UNKNOWN
